verifactu/__init__.py
verifactu/exceptions/__init__.py
verifactu/exceptions/aeat_exception.py
verifactu/exceptions/invalid_model_exception.py
verifactu/models/__init__.py
verifactu/models/computer_system.py
verifactu/models/model.py
verifactu/models/records/__init__.py
verifactu/models/records/breakdown_details.py
verifactu/models/records/cancellation_record.py
verifactu/models/records/corrective_type.py
verifactu/models/records/fiscal_identifier.py
verifactu/models/records/foreign_fiscal_identifier.py
verifactu/models/records/foreign_id_type.py
verifactu/models/records/invoice_identifier.py
verifactu/models/records/invoice_type.py
verifactu/models/records/operation_type.py
verifactu/models/records/record.py
verifactu/models/records/regime_type.py
verifactu/models/records/registration_record.py
verifactu/models/records/tax_type.py
verifactu/models/responses/__init__.py
verifactu/models/responses/aeat_response.py
verifactu/models/responses/item_status.py
verifactu/models/responses/record_type.py
verifactu/models/responses/response_item.py
verifactu/models/responses/response_status.py
verifactu/services/__init__.py
verifactu/services/aeat_client.py
pyverifactu-0.3.2.dist-info/LICENSE
pyverifactu-0.3.2.dist-info/METADATA
pyverifactu-0.3.2.dist-info/WHEEL
pyverifactu-0.3.2.dist-info/top_level.txt
pyverifactu-0.3.2.dist-info/RECORD
