Metadata-Version: 2.1
Name: pyverifactu
Version: 0.3.2
Summary: Python library for generating and submitting invoice records to the Spanish tax authority (AEAT) using the VERI*FACTU system
Author-email: Toni Bagur <toni@inmatic.ai>
License: MIT
Project-URL: Homepage, https://github.com/tonibagur/pyverifactu
Project-URL: Repository, https://github.com/tonibagur/pyverifactu
Project-URL: Documentation, https://github.com/tonibagur/pyverifactu
Keywords: pyverifactu,verifactu,aeat,spain,invoices,tax,facturacion
Classifier: Development Status :: 4 - Beta
Classifier: Intended Audience :: Developers
Classifier: License :: OSI Approved :: MIT License
Classifier: Programming Language :: Python :: 3
Classifier: Programming Language :: Python :: 3.8
Classifier: Programming Language :: Python :: 3.9
Classifier: Programming Language :: Python :: 3.10
Classifier: Programming Language :: Python :: 3.11
Classifier: Programming Language :: Python :: 3.12
Requires-Python: >=3.8
License-File: LICENSE
Requires-Dist: pydantic>=2.0.0
Requires-Dist: requests>=2.28.0
Requires-Dist: lxml>=5.0.0
Requires-Dist: cryptography>=42.0.0
Requires-Dist: python-dateutil>=2.8.0
Provides-Extra: dev
Requires-Dist: pytest>=8.0.0; extra == "dev"
Requires-Dist: pytest-cov>=4.1.0; extra == "dev"
Requires-Dist: pytest-asyncio>=0.23.0; extra == "dev"
Requires-Dist: black>=24.0.0; extra == "dev"
Requires-Dist: mypy>=1.8.0; extra == "dev"
Requires-Dist: ruff>=0.2.0; extra == "dev"
